datasette_chronicle/__init__.py
datasette_chronicle/templates/disable-chronicle.html
datasette_chronicle/templates/enable-chronicle.html
datasette_chronicle-0.3.dist-info/licenses/LICENSE
datasette_chronicle-0.3.dist-info/METADATA
datasette_chronicle-0.3.dist-info/WHEEL
datasette_chronicle-0.3.dist-info/entry_points.txt
datasette_chronicle-0.3.dist-info/top_level.txt
datasette_chronicle-0.3.dist-info/RECORD
