Metadata-Version: 2.4
Name: datasette-chronicle
Version: 0.3
Summary: Use sqlite-chronicle with tables in Datasette
Author: Simon Willison
License-Expression: Apache-2.0
Project-URL: Homepage, https://github.com/datasette/datasette-chronicle
Project-URL: Changelog, https://github.com/datasette/datasette-chronicle/releases
Project-URL: Issues, https://github.com/datasette/datasette-chronicle/issues
Project-URL: CI, https://github.com/datasette/datasette-chronicle/actions
Classifier: Framework :: Datasette
Requires-Python: >=3.9
License-File: LICENSE
Requires-Dist: datasette
Requires-Dist: sqlite-chronicle>=0.4
Provides-Extra: test
Requires-Dist: pytest; extra == "test"
Requires-Dist: pytest-asyncio; extra == "test"
Requires-Dist: sqlite-utils; extra == "test"
Dynamic: license-file
